flake8_define_class_attributes/__init__.py
flake8_define_class_attributes/ast_walker.py
flake8_define_class_attributes/checker.py
flake8_define_class_attributes-0.2.1.dist-info/licenses/LICENSE
flake8_define_class_attributes-0.2.1.dist-info/WHEEL
flake8_define_class_attributes-0.2.1.dist-info/entry_points.txt
flake8_define_class_attributes-0.2.1.dist-info/METADATA
flake8_define_class_attributes-0.2.1.dist-info/RECORD
