Metadata-Version: 2.4
Name: flake8-define-class-attributes
Version: 0.2.1
Summary: Check that class attributes are defined at the top level
Author: sco1
Author-email: sco1 <sco1.git@gmail.com>
License-Expression: MIT
License-File: LICENSE
Classifier: Development Status :: 4 - Beta
Classifier: Intended Audience :: Developers
Classifier: Operating System :: OS Independent
Classifier: Programming Language :: Python :: 3 :: Only
Classifier: Programming Language :: Python :: 3.11
Classifier: Programming Language :: Python :: 3.12
Classifier: Programming Language :: Python :: 3.13
Classifier: Programming Language :: Python :: 3.14
Classifier: Typing :: Typed
Requires-Dist: flake8>=5.0
Requires-Python: >=3.11
Project-URL: Changelog, https://github.com/sco1/flake8-define-class-attributes/blob/main/CHANGELOG.md
Project-URL: Documentation, https://github.com/sco1/flake8-define-class-attributes/blob/main/README.md
Project-URL: Homepage, https://github.com/sco1/
Project-URL: Issues, https://github.com/sco1/flake8-define-class-attributes/issues
Project-URL: Repository, https://github.com/sco1/flake8-define-class-attributes.git
